{
    "nixpkgs": {
        "branch": "nixos-20.03",
        "description": "A read-only mirror of NixOS/nixpkgs tracking the released channels. Send issues and PRs to",
        "homepage": "https://github.com/NixOS/nixpkgs",
        "owner": "NixOS",
        "repo": "nixpkgs-channels",
        "rev": "4d373182597cff60b3a820affb5a73dd274e205b",
        "sha256": "1kvsnlsq1czgk085rllg1b427n6lv5w3a2z1igfc95n81jpvcf58",
        "type": "tarball",
        "url": "https://github.com/NixOS/nixpkgs-channels/archive/4d373182597cff60b3a820affb5a73dd274e205b.tar.gz",
        "url_template": "https://github.com/<owner>/<repo>/archive/<rev>.tar.gz"
    }
}
